ENToolbox.py
MANIFEST.in
README.txt
setup.py
ENToolbox.egg-info/PKG-INFO
ENToolbox.egg-info/SOURCES.txt
ENToolbox.egg-info/dependency_links.txt
ENToolbox.egg-info/top_level.txt