Metadata-Version: 1.0
Name: ENToolbox
Version: 0.1
Summary: A set of tools for interacting with Evernote API in a simplified manner
Home-page: UNKNOWN
Author: Scott Kammlade
Author-email: noreply.garfield@gmail.com
License: MIT
Platform: UNKNOWN
